fcst/__init__.py
fcst/py.typed
fcst/version.py
fcst/allocation/__init__.py
fcst/allocation/_allocation.py
fcst/automation/__init__.py
fcst/automation/_forecasting_automation.py
fcst/common/__init__.py
fcst/common/configs.py
fcst/common/types.py
fcst/evaluation/__init__.py
fcst/evaluation/backtesting.py
fcst/evaluation/model_selection.py
fcst/forecasting/__init__.py
fcst/forecasting/ensemble.py
fcst/forecasting/forecasting.py
fcst/horizon/__init__.py
fcst/metrics/__init__.py
fcst/metrics/_metrics.py
fcst/models/__init__.py
fcst/models/_models.py
fcst/models/autots.py
fcst/models/model_list.py
fcst/models/multivar.py
fcst/preprocessing/__init__.py
fcst/preprocessing/_preprocessing.py
fcst-0.8.11.dist-info/METADATA
fcst-0.8.11.dist-info/WHEEL
fcst-0.8.11.dist-info/licenses/LICENSE
fcst-0.8.11.dist-info/RECORD
