Metadata-Version: 2.4
Name: fcst
Version: 0.8.11
Summary: Forecasting utilities, time-series preprocessing, rolling back-test and ensemble forecasting from model selection
Project-URL: Repository, https://github.com/anuponwa/fcst
Author-email: Anupong Wannakrairot <anuponwa@scg.com>
License: MIT License
License-File: LICENSE
Classifier: Development Status :: 4 - Beta
Classifier: Intended Audience :: Developers
Classifier: Intended Audience :: Information Technology
Classifier: Intended Audience :: Science/Research
Classifier: License :: OSI Approved :: MIT License
Classifier: Operating System :: OS Independent
Classifier: Programming Language :: Python
Classifier: Programming Language :: Python :: 3
Classifier: Programming Language :: Python :: 3.12
Classifier: Topic :: Scientific/Engineering :: Information Analysis
Requires-Python: >=3.10
Requires-Dist: autots>=0.6.21
Requires-Dist: pandas>=2.2.3
Requires-Dist: prophet>=1.1.6
Requires-Dist: sktime>=0.36.0
Requires-Dist: statsforecast>=2.0.1
Requires-Dist: statsmodels>=0.14.4
